{
  "video_id": "ipA6CTwL2Ik",
  "title": "Trái tim bệnh nhân và Trái tim bác sĩ: Những điều ít ai nói với bạn",
  "source_url": "https://www.youtube.com/watch?v=ipA6CTwL2Ik",
  "main_topics": [],
  "summary": "Tóm tắt không khả dụng",
  "detailed_summary": "",
  "key_points": [],
  "health_advice": [],
  "warnings": [],
  "related_conditions": [],
  "mechanisms": [],
  "specific_numbers": [],
  "protocols": [],
  "myths_debunked": [],
  "key_quotes": [],
  "processed_at": "2026-06-01T21:53:18.384003",
  "transcript_coverage": 0.65,
  "quality_score": 0.3,
  "categories": [
    "diseases"
  ]
}