{
  "video_id": "xGzltIzg7gA",
  "title": "Những sự thật khoa học về Dư lượng thuốc trừ sâu trong rau củ quả",
  "source_url": "https://www.youtube.com/watch?v=xGzltIzg7gA",
  "main_topics": [],
  "summary": "Tóm tắt không khả dụng",
  "detailed_summary": "",
  "key_points": [],
  "health_advice": [],
  "warnings": [],
  "related_conditions": [],
  "mechanisms": [],
  "specific_numbers": [],
  "protocols": [],
  "myths_debunked": [],
  "key_quotes": [],
  "processed_at": "2026-06-01T21:53:45.938940",
  "transcript_coverage": 1.0,
  "quality_score": 0.3,
  "categories": [
    "nutrition",
    "diseases",
    "medications"
  ]
}